<?xml version="1.0" encoding="utf-8"?>
<abapGit version="v1.0.0">
 <asx:abap xmlns:asx="http://www.sap.com/abapxml" version="1.0">
  <asx:values>
   <PROGDIR>
    <NAME>SAPLZFG_EXCEL_INTERFACE</NAME>
    <DBAPL>S</DBAPL>
    <DBNA>D$</DBNA>
    <SUBC>F</SUBC>
    <APPL>S</APPL>
    <RLOAD>E</RLOAD>
    <FIXPT>X</FIXPT>
    <LDBNAME>D$S</LDBNAME>
    <UCCHECK>X</UCCHECK>
   </PROGDIR>
   <TPOOL>
    <item>
     <ID>I</ID>
     <KEY>008</KEY>
     <ENTRY>Save file successful</ENTRY>
     <LENGTH>20</LENGTH>
    </item>
    <item>
     <ID>I</ID>
     <KEY>009</KEY>
     <ENTRY>Do you want to open excel file?</ENTRY>
     <LENGTH>31</LENGTH>
    </item>
    <item>
     <ID>I</ID>
     <KEY>010</KEY>
     <ENTRY>Save file unsuccessful</ENTRY>
     <LENGTH>22</LENGTH>
    </item>
   </TPOOL>
  </asx:values>
 </asx:abap>
</abapGit>
